src/PE.v
module PE #(
    parameter DATA_WIDTH = 16,
    parameter ACCUM_WIDTH = 40 // 256 consecutive multiplications possible without overflow for 16-bit signed inputs
)(
    input  wire                     clk,
    input  wire                     rst,
    input  wire signed [DATA_WIDTH-1:0]  in_x, 
    input  wire signed [DATA_WIDTH-1:0]  in_y,  
    output reg  signed [DATA_WIDTH-1:0]  out_x,  // Registered activation to neighbor
    output reg  signed [DATA_WIDTH-1:0]  out_y,  // Registered weight to neighbor
    output reg  signed [ACCUM_WIDTH-1:0] out_c   // Internal Accumulator output
);

    // Force the synthesis tool to wrap this specific register inside a hardware DSP slice
    (* use_dsp = "yes" *) reg signed [ACCUM_WIDTH-1:0] accumulator;

    // Internal pipeline registers to match DSP physical layout
    reg signed [DATA_WIDTH-1:0] x_reg;
    reg signed [DATA_WIDTH-1:0] y_reg;
    reg signed [(2*DATA_WIDTH)-1:0] product_reg;

    always @(posedge clk) begin
        if (rst) begin
            x_reg       <= 0;
            y_reg       <= 0;
            product_reg <= 0;
            accumulator <= 0;
            out_x       <= 0;
            out_y       <= 0;
            out_c       <= 0;
        end else begin
            // Pipeline Stage 1: Latch inputs into local registers
            x_reg <= in_x;
            y_reg <= in_y;

            // Pipeline Stage 2: Multiply latched values
            product_reg <= x_reg * y_reg;

            // Pipeline Stage 3: Accumulate the product in the DSP core
            accumulator <= accumulator + product_reg;

            // Delay outputs by one cycle to safely cross to the next PE boundary
            out_x <= x_reg;
            out_y <= y_reg;
            out_c <= accumulator;
        end
    end

endmodule

sim/tb_PE.v
`timescale 1ns/1ps

module tb_PE;

    parameter DATA_WIDTH = 16;
    parameter ACCUM_WIDTH = 40;

    reg clk;
    reg rst;
    reg signed [DATA_WIDTH-1:0] in_x;
    reg signed [DATA_WIDTH-1:0] in_y;
    wire signed [DATA_WIDTH-1:0] out_x;
    wire signed [DATA_WIDTH-1:0] out_y;
    wire signed [ACCUM_WIDTH-1:0] out_c;

    PE #(
        .DATA_WIDTH(DATA_WIDTH),
        .ACCUM_WIDTH(ACCUM_WIDTH)
    ) uut (
        .clk(clk),
        .rst(rst),
        .in_x(in_x),
        .in_y(in_y),
        .out_x(out_x),
        .out_y(out_y),
        .out_c(out_c)
    );

    always #10 clk = ~clk;

    integer   errors;
    integer   cycle_cnt;

    reg signed [DATA_WIDTH-1:0]  hist_x [0:31];
    reg signed [DATA_WIDTH-1:0]  hist_y [0:31];

    // Drive (x,y) on each negedge.
    // At negedge N, out_x/out_y reflect inputs from N-2 negedges ago.
    // out_c reflects the running accumulation of all products from N-4 negedges ago.
    task cycle;
        input signed [DATA_WIDTH-1:0] x;
        input signed [DATA_WIDTH-1:0] y;
        reg signed [ACCUM_WIDTH-1:0] exp_c;
        integer i;
        begin
            @(negedge clk);
            in_x <= x;
            in_y <= y;

            if (cycle_cnt >= 2) begin
                if (out_x !== hist_x[cycle_cnt-2] || out_y !== hist_y[cycle_cnt-2]) begin
                    $error("[%0d] out_x/y MISMATCH: got (%d,%d) exp (%d,%d)",
                           cycle_cnt, out_x, out_y,
                           hist_x[cycle_cnt-2], hist_y[cycle_cnt-2]);
                    errors = errors + 1;
                end
            end

            if (cycle_cnt >= 4) begin
                exp_c = 0;
                for (i = 0; i <= cycle_cnt-4; i = i + 1)
                    exp_c = exp_c + hist_x[i] * hist_y[i];
                if (out_c !== exp_c) begin
                    $error("[%0d] out_c MISMATCH: got %d exp %d (diff=%d)",
                           cycle_cnt, out_c, exp_c, out_c - exp_c);
                    errors = errors + 1;
                end else begin
                    $display("[%0d] PASS: out_x=%d out_y=%d out_c=%d",
                             cycle_cnt, out_x, out_y, out_c);
                end
            end else if (cycle_cnt >= 2) begin
                $display("[%0d] PASS: out_x=%d out_y=%d out_c=%d",
                         cycle_cnt, out_x, out_y, out_c);
            end

            hist_x[cycle_cnt] = x;
            hist_y[cycle_cnt] = y;
            cycle_cnt = cycle_cnt + 1;
        end
    endtask

    // Wipe history and drive zeros after reset
    task reset_pipeline;
        begin
            rst = 1;
            repeat (2) @(posedge clk);
            rst = 0;
            cycle_cnt = 0;
            // Blocking assignment to clear inputs immediately
            in_x = 0;
            in_y = 0;
        end
    endtask

    initial begin
        $dumpfile("tb_PE.vcd");
        $dumpvars(0, tb_PE);

        clk = 0;
        rst = 1;
        in_x = 0;
        in_y = 0;
        errors   = 0;
        cycle_cnt = 0;

        // Initial reset for 3 posedges
        repeat (3) @(posedge clk);
        rst = 0;
        in_x = 0;
        in_y = 0;

        // Sync to negedge, then check and start driving
        @(negedge clk);
        $display("=== Reset state: out_x=%d out_y=%d out_c=%d ===",
                 out_x, out_y, out_c);

        // =============================================
        // Test 1: Basic MAC 2*3 + 4*5
        // =============================================
        $display("\n=== Test 1: Basic MAC 2*3 + 4*5 ===");
        cycle(16'd2, 16'd3);   // cyc 0
        cycle(16'd4, 16'd5);   // cyc 1
        cycle(16'd0, 16'd0);   // cyc 2: out_x/y = (2,3)
        cycle(16'd0, 16'd0);   // cyc 3: out_x/y = (4,5)
        cycle(16'd0, 16'd0);   // cyc 4: out_c = 6
        cycle(16'd0, 16'd0);   // cyc 5: out_c = 26

        // =============================================
        // Test 2: Negative values
        // =============================================
        $display("\n=== Test 2: Negative values (-3)*4 + 2*(-5) ===");
        cycle(-16'd3, 16'd4);    // cyc 6
        cycle(16'd2, -16'd5);    // cyc 7
        cycle(16'd0, 16'd0);     // cyc 8
        cycle(16'd0, 16'd0);     // cyc 9
        cycle(16'd0, 16'd0);     // cyc10

        // =============================================
        // Test 3: Reset during operation
        // =============================================
        $display("\n=== Test 3: Reset during operation ===");
        cycle(16'd1, 16'd2);     // cyc11: last input before reset
        reset_pipeline();

        // Verify reset cleared everything
        @(negedge clk);
        if (out_x !== 0 || out_y !== 0 || out_c !== 0) begin
            $error("Reset check FAIL: out_x=%d out_y=%d out_c=%d",
                   out_x, out_y, out_c);
            errors = errors + 1;
        end else begin
            $display("Reset check PASS");
        end

        // =============================================
        // Test 4: Back-to-back MAC
        // =============================================
        $display("\n=== Test 4: Back-to-back MAC 7*3, 2*6, 1*9 ===");
        cycle(16'd7, 16'd3);     // cyc 0
        cycle(16'd2, 16'd6);     // cyc 1
        cycle(16'd1, 16'd9);     // cyc 2: out = (7,3)
        cycle(16'd0, 16'd0);     // cyc 3: out = (2,6)
        cycle(16'd0, 16'd0);     // cyc 4: out_c = 21
        cycle(16'd0, 16'd0);     // cyc 5: out_c = 33
        cycle(16'd0, 16'd0);     // cyc 6: out_c = 42

        // =============================================
        // Test 5: Large values
        // =============================================
        $display("\n=== Test 5: Max 16-bit signed: 32767 * 32767 ===");
        cycle(16'd32767, 16'd32767);  // cyc 7
        cycle(16'd0, 16'd0);          // cyc 8
        cycle(16'd0, 16'd0);          // cyc 9: out = (32767,32767)
        cycle(16'd0, 16'd0);          // cyc10: out = (0,0)
        cycle(16'd0, 16'd0);          // cyc11: out_c = 1073676289

        // =============================================
        // Summary
        // =============================================
        $display("\n================================");
        if (errors === 0)
            $display("*** ALL TESTS PASSED ***");
        else
            $display("*** %0d TEST(S) FAILED ***", errors);
        #100 $finish;
    end

endmodule

build/tb_PE.vcd
$date
	Tue Jun  2 22:09:04 2026
$end
$version
	Icarus Verilog
$end
$timescale
	1ps
$end
$scope module tb_PE $end
$var wire 16 ! out_y [15:0] $end
$var wire 16 " out_x [15:0] $end
$var wire 40 # out_c [39:0] $end
$var parameter 32 $ ACCUM_WIDTH $end
$var parameter 32 % DATA_WIDTH $end
$var reg 1 & clk $end
$var reg 16 ' in_x [15:0] $end
$var reg 16 ( in_y [15:0] $end
$var reg 1 ) rst $end
$var integer 32 * cycle_cnt [31:0] $end
$var integer 32 + errors [31:0] $end
$scope module uut $end
$var wire 1 & clk $end
$var wire 16 , in_x [15:0] $end
$var wire 16 - in_y [15:0] $end
$var wire 1 ) rst $end
$var parameter 32 . ACCUM_WIDTH $end
$var parameter 32 / DATA_WIDTH $end
$var reg 40 0 accumulator [39:0] $end
$var reg 40 1 out_c [39:0] $end
$var reg 16 2 out_x [15:0] $end
$var reg 16 3 out_y [15:0] $end
$var reg 32 4 product_reg [31:0] $end
$var reg 16 5 x_reg [15:0] $end
$var reg 16 6 y_reg [15:0] $end
$upscope $end
$scope task cycle $end
$var reg 40 7 exp_c [39:0] $end
$var reg 16 8 x [15:0] $end
$var reg 16 9 y [15:0] $end
$var integer 32 : i [31:0] $end
$upscope $end
$scope task reset_pipeline $end
$upscope $end
$upscope $end
$enddefinitions $end
$comment Show the parameter values. $end
$dumpall
b10000 /
b101000 .
b10000 %
b101000 $
$end
#0
$dumpvars
bx :
bx 9
bx 8
bx 7
bx 6
bx 5
bx 4
bx 3
bx 2
bx 1
bx 0
b0 -
b0 ,
b0 +
b0 *
1)
b0 (
b0 '
0&
bx #
bx "
bx !
$end
#10000
b0 #
b0 1
b0 !
b0 3
b0 "
b0 2
b0 0
b0 4
b0 6
b0 5
1&
#20000
0&
#30000
1&
#40000
0&
#50000
0)
1&
#60000
b11 9
b10 8
0&
#70000
1&
#80000
b11 (
b11 -
b10 '
b10 ,
b101 9
b100 8
b1 *
0&
#90000
b11 6
b10 5
1&
#100000
b101 (
b101 -
b100 '
b100 ,
b0 9
b0 8
b10 *
0&
#110000
b11 !
b11 3
b10 "
b10 2
b110 4
b101 6
b100 5
1&
#120000
b0 (
b0 -
b0 '
b0 ,
b11 *
0&
#130000
b101 !
b101 3
b100 "
b100 2
b110 0
b10100 4
b0 6
b0 5
1&
#140000
b100 *
0&
#150000
b110 #
b110 1
b0 !
b0 3
b0 "
b0 2
b11010 0
b0 4
1&
#160000
b101 *
b1 :
b110 7
0&
#170000
b11010 #
b11010 1
1&
#180000
b100 9
b1111111111111101 8
b110 *
b10 :
b11010 7
0&
#190000
1&
#200000
b100 (
b100 -
b1111111111111101 '
b1111111111111101 ,
b1111111111111011 9
b10 8
b111 *
b11 :
b11010 7
0&
#210000
b100 6
b1111111111111101 5
1&
#220000
b1111111111111011 (
b1111111111111011 -
b10 '
b10 ,
b0 9
b0 8
b1000 *
b100 :
b11010 7
0&
#230000
b100 !
b100 3
b1111111111111101 "
b1111111111111101 2
b11111111111111111111111111110100 4
b1111111111111011 6
b10 5
1&
#240000
b0 (
b0 -
b0 '
b0 ,
b1001 *
b101 :
b11010 7
0&
#250000
b1111111111111011 !
b1111111111111011 3
b10 "
b10 2
b1110 0
b11111111111111111111111111110110 4
b0 6
b0 5
1&
#260000
b1010 *
b110 :
b11010 7
0&
#270000
b1110 #
b1110 1
b0 !
b0 3
b0 "
b0 2
b100 0
b0 4
1&
#280000
b10 9
b1 8
b1011 *
b111 :
b1110 7
0&
#290000
b100 #
b100 1
1&
#300000
b10 (
b10 -
b1 '
b1 ,
1)
b1100 *
b1000 :
b100 7
0&
#310000
b0 #
b0 1
b0 0
1&
#320000
0&
#330000
b0 (
b0 -
b0 '
b0 ,
b0 *
0)
1&
#340000
b11 9
b111 8
0&
#350000
1&
#360000
b11 (
b11 -
b111 '
b111 ,
b110 9
b10 8
b1 *
0&
#370000
b11 6
b111 5
1&
#380000
b110 (
b110 -
b10 '
b10 ,
b1001 9
b1 8
b10 *
0&
#390000
b11 !
b11 3
b111 "
b111 2
b10101 4
b110 6
b10 5
1&
#400000
b1001 (
b1001 -
b1 '
b1 ,
b0 9
b0 8
b11 *
0&
#410000
b110 !
b110 3
b10 "
b10 2
b10101 0
b1100 4
b1001 6
b1 5
1&
#420000
b0 (
b0 -
b0 '
b0 ,
b100 *
0&
#430000
b10101 #
b10101 1
b1001 !
b1001 3
b1 "
b1 2
b100001 0
b1001 4
b0 6
b0 5
1&
#440000
b101 *
b1 :
b10101 7
0&
#450000
b100001 #
b100001 1
b0 !
b0 3
b0 "
b0 2
b101010 0
b0 4
1&
#460000
b110 *
b10 :
b100001 7
0&
#470000
b101010 #
b101010 1
1&
#480000
b111111111111111 9
b111111111111111 8
b111 *
b11 :
b101010 7
0&
#490000
1&
#500000
b111111111111111 (
b111111111111111 -
b111111111111111 '
b111111111111111 ,
b0 9
b0 8
b1000 *
b100 :
b101010 7
0&
#510000
b111111111111111 6
b111111111111111 5
1&
#520000
b0 (
b0 -
b0 '
b0 ,
b1001 *
b101 :
b101010 7
0&
#530000
b111111111111111 !
b111111111111111 3
b111111111111111 "
b111111111111111 2
b111111111111110000000000000001 4
b0 6
b0 5
1&
#540000
b1010 *
b110 :
b101010 7
0&
#550000
b0 !
b0 3
b0 "
b0 2
b111111111111110000000000101011 0
b0 4
1&
#560000
b1011 *
b111 :
b101010 7
0&
#570000
b111111111111110000000000101011 #
b111111111111110000000000101011 1
1&
#580000
b1100 *
b1000 :
b111111111111110000000000101011 7
0&
